funtes/bfloat16_processor.v
`timescale 1ns / 1ps

module bfloat16_processor (
    input clk,
    input rst,
    // Interfaz SPI
    input sck,        // Reloj SPI
    input mosi,       // Datos del master hacia el esclavo
    output reg miso,  // Datos del esclavo hacia el master
    input cs,         // Chip select (activo bajo)
    // Salidas opcionales para depuración
    output reg [15:0] acc_monitor, // Permite monitorear el acumulador
    output reg ready               // Señal de listo
);

// ---------------------------
// Registros internos
// ---------------------------
reg [15:0] acc;               // Acumulador interno
reg [15:0] instruction_reg;   // Registro de instrucción recibida
reg [15:0] operand1_reg;      // Primer operando
reg [15:0] operand2_reg;      // Segundo operando
reg [15:0] result_reg;        // Registro de resultado

// ---------------------------
// Señales de control
// ---------------------------
reg [3:0] state;              // Estado de la máquina de estados
reg [3:0] current_opcode;     // Código de instrucción actual

// ---------------------------
// Interfaz SPI
// ---------------------------
reg [15:0] spi_shift_in;      // Registro de desplazamiento para entrada SPI
reg [15:0] spi_shift_out;     // Registro de desplazamiento para salida SPI
reg [4:0] spi_bit_counter;    // Contador de bits recibidos
reg spi_transfer_active;      // Indica si hay transferencia activa
reg last_cs;                  // Guarda el valor previo de CS para detectar flancos

// ---------------------------
// Operaciones de punto flotante simplificadas
// ---------------------------
wire [15:0] add_result;       // Resultado de suma
wire [15:0] mul_result;       // Resultado de multiplicación
wire [15:0] div_result;       // Resultado de división

// ---------------------------
// Inicialización de registros
// ---------------------------
initial begin
    acc = 16'b0;
    instruction_reg = 16'b0;
    operand1_reg = 16'b0;
    operand2_reg = 16'b0;
    result_reg = 16'b0;
    state = 0;
    current_opcode = 0;
    spi_shift_in = 16'b0;
    spi_shift_out = 16'b0;
    spi_bit_counter = 0;
    spi_transfer_active = 0;
    last_cs = 1;
    miso = 0;
    acc_monitor = 16'b0;
    ready = 0;
end

// ---------------------------
// Operaciones matemáticas simplificadas
// NOTA: solo funcionalidad de prueba, no IEEE 754 exacto
// ---------------------------
assign add_result = operand1_reg + operand2_reg; // Suma simplificada

assign mul_result = {operand1_reg[15] ^ operand2_reg[15],  // Signo
                     operand1_reg[14:7] + operand2_reg[14:7] - 8'd15, // Exponente
                     (operand1_reg[6:0] * operand2_reg[6:0]) >> 7};   // Mantisa

assign div_result = {operand1_reg[15] ^ operand2_reg[15],  // Signo
                     operand1_reg[14:7] - operand2_reg[14:7] + 8'd15, // Exponente
                     (operand1_reg[6:0] << 7) / operand2_reg[6:0]};   // Mantisa

// ---------------------------
// Procesamiento de entrada SPI
// ---------------------------
always @(posedge clk or posedge rst) begin
    if (rst) begin
        // Reset de registros SPI y estado
        spi_shift_in <= 16'b0;
        spi_bit_counter <= 0;
        spi_transfer_active <= 0;
        last_cs <= 1;
        state <= 0;
        ready <= 0;
    end else begin
        last_cs <= cs;               // Guardar estado anterior de CS
        ready <= (state == 0);       // Listo si está esperando instrucción
        
        // Detectar flanco descendente de CS: inicio de transferencia
        if (last_cs && !cs) begin
            spi_transfer_active <= 1;
            spi_bit_counter <= 0;
            spi_shift_in <= 16'b0;
        end
        
        // Detectar flanco ascendente de CS: fin de transferencia
        if (!last_cs && cs) begin
            spi_transfer_active <= 0;
            if (spi_bit_counter == 16) begin
                // Palabra completa recibida
                case (state)
                    0: begin // Esperando instrucción
                        instruction_reg <= {spi_shift_in[0], spi_shift_in[1], spi_shift_in[2], spi_shift_in[3],
                                           spi_shift_in[4], spi_shift_in[5], spi_shift_in[6], spi_shift_in[7],
                                           spi_shift_in[8], spi_shift_in[9], spi_shift_in[10], spi_shift_in[11],
                                           spi_shift_in[12], spi_shift_in[13], spi_shift_in[14], spi_shift_in[15]};
                        current_opcode <= spi_shift_in[3:0]; // Tomar 4 LSB como opcode
                        state <= 1; // Pasar a recibir primer operando
                    end
                    1: begin // Esperando primer operando
                        operand1_reg <= {spi_shift_in[0], spi_shift_in[1], spi_shift_in[2], spi_shift_in[3],
                                        spi_shift_in[4], spi_shift_in[5], spi_shift_in[6], spi_shift_in[7],
                                        spi_shift_in[8], spi_shift_in[9], spi_shift_in[10], spi_shift_in[11],
                                        spi_shift_in[12], spi_shift_in[13], spi_shift_in[14], spi_shift_in[15]};
                        // Para operaciones que requieren dos operandos
                        if (current_opcode >= 3 && current_opcode <= 6) begin
                            state <= 2; // Esperar segundo operando
                        end else begin
                            state <= 3; // Ejecutar operación
                        end
                    end
                    2: begin // Esperando segundo operando
                        operand2_reg <= {spi_shift_in[0], spi_shift_in[1], spi_shift_in[2], spi_shift_in[3],
                                        spi_shift_in[4], spi_shift_in[5], spi_shift_in[6], spi_shift_in[7],
                                        spi_shift_in[8], spi_shift_in[9], spi_shift_in[10], spi_shift_in[11],
                                        spi_shift_in[12], spi_shift_in[13], spi_shift_in[14], spi_shift_in[15]};
                        state <= 3; // Ejecutar operación
                    end
                    default: state <= 0;
                endcase
            end
        end
        
        // Desplazar datos de entrada en flanco de subida de SCK
        if (!cs && sck && spi_transfer_active) begin
            spi_shift_in <= {mosi, spi_shift_in[15:1]}; // LSB primero
            spi_bit_counter <= spi_bit_counter + 1;
        end
        
        // ---------------------------
        // Ejecución de la operación
        // ---------------------------
        case (state)
            3: begin
                case (current_opcode)
                    0: begin // ZERO: limpiar acumulador
                        acc <= 16'b0;
                        result_reg <= 16'b0;
                        state <= 0;
                    end
                    1: begin // SET_ACC: cargar acumulador
                        acc <= operand1_reg;
                        result_reg <= operand1_reg;
                        state <= 0;
                    end
                    2: begin // LOAD_ACC: devolver acumulador
                        result_reg <= acc;
                        state <= 0;
                    end
                    3: begin // ADD2: suma simple
                        result_reg <= add_result;
                        state <= 0;
                    end
                    4: begin // SUB2: resta simplificada
                        result_reg <= add_result;
                        state <= 0;
                    end
                    5: begin // MPY2: multiplicación
                        result_reg <= mul_result;
                        state <= 0;
                    end
                    6: begin // DIV2: división
                        result_reg <= div_result;
                        state <= 0;
                    end
                    7: begin // SUM: acumular suma
                        acc <= add_result;
                        result_reg <= add_result;
                        state <= 1; // Esperar siguiente operando
                    end
                    8: begin // SUB: acumular resta
                        acc <= add_result;
                        result_reg <= add_result;
                        state <= 1;
                    end
                    9: begin // MAC: multiplicar y acumular
                        acc <= mul_result + acc;
                        result_reg <= acc;
                        state <= 1;
                    end
                    10: begin // MAS: multiplicar y restar del acumulador
                        acc <= acc - mul_result;
                        result_reg <= acc;
                        state <= 1;
                    end
                    default: begin
                        state <= 0;
                    end
                endcase
            end
        endcase
    end
end

// ---------------------------
// Salida SPI
// ---------------------------
always @(posedge clk or posedge rst) begin
    if (rst) begin
        spi_shift_out <= 16'b0;
        miso <= 0;
    end else begin
        // Preparar datos de salida LSB primero
        if (!cs && state == 0) begin
            spi_shift_out <= {result_reg[0], result_reg[1], result_reg[2], result_reg[3],
                             result_reg[4], result_reg[5], result_reg[6], result_reg[7],
                             result_reg[8], result_reg[9], result_reg[10], result_reg[11],
                             result_reg[12], result_reg[13], result_reg[14], result_reg[15]};
        end
        
        // Desplazar datos de salida en flanco de bajada de SCK
        if (!cs && !sck && spi_transfer_active) begin
            miso <= spi_shift_out[0];
            spi_shift_out <= {1'b0, spi_shift_out[15:1]};
        end
    end
end

// ---------------------------
// Monitoreo del acumulador
// ---------------------------
always @(posedge clk) begin
    acc_monitor <= acc; // Actualiza salida para depuración
end

endmodule

funtes/tb_bfloat16_processor.v
`timescale 1ns / 1ps

module tb_bfloat16_processor_full;

    // === Entradas del DUT ===
    reg clk;
    reg rst;
    reg sck;
    reg mosi;
    reg cs;

    // === Salidas del DUT ===
    wire miso;
    wire [15:0] acc_monitor;
    wire ready;

    // === Instancia del DUT ===
    bfloat16_processor dut (
        .clk(clk),
        .rst(rst),
        .sck(sck),
        .mosi(mosi),
        .miso(miso),
        .cs(cs),
        .acc_monitor(acc_monitor),
        .ready(ready)
    );

    // === Generadores de reloj ===
    initial clk = 0;
    always #5 clk = ~clk; // 100 MHz

    initial sck = 0;
    always #20 sck = ~sck; // Frecuencia SPI más lenta

    // ===============================
    // Bloque de pruebas: un opcode por prueba
    // ===============================
    initial begin
        // --- Archivo VCD ---
        $dumpfile("tb_bfloat16_processor_full.vcd");
        $dumpvars(0, tb_bfloat16_processor_full);

        // Reset inicial
        rst = 1; cs = 1; mosi = 0;
        #50;
        rst = 0;
        #10;

        // ===============================
        // 00: ZERO
        // ===============================
        send_spi_word(16'h0000); 
        #200;

        // ===============================
        // 01: SET_ACC (1.5)
        // ===============================
        send_spi_word(16'h0001); 
        send_spi_word(16'h3FC0); 
        #200;

        // ===============================
        // 02: LOAD_ACC
        // ===============================
        send_spi_word(16'h0002); 
        #200;

        // ===============================
        // 03: ADD2 (1.5 + 2.0)
        // ===============================
        send_spi_word(16'h0003);
        send_spi_word(16'h3FC0);
        send_spi_word(16'h4000);
        #200;

        // ===============================
        // 04: SUB2 (2.0 - 1.5)
        // ===============================
        send_spi_word(16'h0004);
        send_spi_word(16'h4000);
        send_spi_word(16'h3FC0);
        #200;

        // ===============================
        // 05: MPY2 (1.5 * 2.0)
        // ===============================
        send_spi_word(16'h0005);
        send_spi_word(16'h3FC0);
        send_spi_word(16'h4000);
        #200;

        // ===============================
        // 06: DIV2 (2.0 / 1.5)
        // ===============================
        send_spi_word(16'h0006);
        send_spi_word(16'h4000);
        send_spi_word(16'h3FC0);
        #200;

        // ===============================
        // 07: SUM (acumular 0.5)
        // ===============================
        send_spi_word(16'h0007);
        send_spi_word(16'h3F00); // 0.5
        #200;

        // ===============================
        // 08: SUB (restar 0.25 acumulado)
        // ===============================
        send_spi_word(16'h0008);
        send_spi_word(16'h3E80); // 0.25
        #200;

        // ===============================
        // 09: MAC (1.0 * 2.0 -> acumular)
        // ===============================
        send_spi_word(16'h0009);
        send_spi_word(16'h3F80); // 1.0
        send_spi_word(16'h4000); // 2.0
        #200;

        // ===============================
        // 10: MAS (1.5 * 2.0 -> restar acumulador)
        // ===============================
        send_spi_word(16'h000A);
        send_spi_word(16'h3FC0); // 1.5
        send_spi_word(16'h4000); // 2.0
        #200;

        // ===============================
        // FIN DE PRUEBAS
        // ===============================
        #50;
        $finish;
    end

    // ===============================
    // Tarea para enviar palabra SPI (LSB primero)
    // ===============================
    task send_spi_word;
        input [15:0] data;
        integer i;
        begin
            cs = 0;
            for (i = 0; i < 16; i = i + 1) begin
                mosi = data[i];    
                #40;               
            end
            cs = 1;
            #40;
        end
    endtask

endmodule

funtes/tb_bfloat16_processor_full.vcd
$date
	Sat Nov 22 17:25:20 2025
$end
$version
	Icarus Verilog
$end
$timescale
	1ps
$end
$scope module tb_bfloat16_processor_full $end
$var wire 1 ! ready $end
$var wire 1 " miso $end
$var wire 16 # acc_monitor [15:0] $end
$var reg 1 $ clk $end
$var reg 1 % cs $end
$var reg 1 & mosi $end
$var reg 1 ' rst $end
$var reg 1 ( sck $end
$scope module dut $end
$var wire 1 $ clk $end
$var wire 1 % cs $end
$var wire 1 & mosi $end
$var wire 1 ' rst $end
$var wire 1 ( sck $end
$var wire 16 ) mul_result [15:0] $end
$var wire 16 * div_result [15:0] $end
$var wire 16 + add_result [15:0] $end
$var reg 16 , acc [15:0] $end
$var reg 16 - acc_monitor [15:0] $end
$var reg 4 . current_opcode [3:0] $end
$var reg 16 / instruction_reg [15:0] $end
$var reg 1 0 last_cs $end
$var reg 1 " miso $end
$var reg 16 1 operand1_reg [15:0] $end
$var reg 16 2 operand2_reg [15:0] $end
$var reg 1 ! ready $end
$var reg 16 3 result_reg [15:0] $end
$var reg 5 4 spi_bit_counter [4:0] $end
$var reg 16 5 spi_shift_in [15:0] $end
$var reg 16 6 spi_shift_out [15:0] $end
$var reg 1 7 spi_transfer_active $end
$var reg 4 8 state [3:0] $end
$upscope $end
$scope task send_spi_word $end
$var reg 16 9 data [15:0] $end
$var integer 32 : i [31:0] $end
$upscope $end
$upscope $end
$enddefinitions $end
$comment Show the parameter values. $end
$dumpall
$end
#0
$dumpvars
bx :
bx 9
b0 8
07
b0 6
b0 5
b0 4
b0 3
b0 2
b0 1
10
b0 /
b0 .
b0 -
b0 ,
b0 +
b1111xxxxxxx *
b111100010000000 )
0(
1'
0&
1%
0$
b0 #
0"
0!
$end
#5000
1$
#10000
0$
#15000
1$
#20000
0$
1(
#25000
1$
#30000
0$
#35000
1$
#40000
0$
0(
#45000
1$
#50000
0$
0'
#55000
1!
1$
#60000
0$
b0 :
0%
b0 9
1(
#65000
17
00
1$
#70000
0$
#75000
b1 4
1$
#80000
0$
0(
#85000
1$
#90000
0$
#95000
1$
#100000
0$
1(
b1 :
#105000
b10 4
1$
#110000
0$
#115000
b11 4
1$
#120000
0$
0(
#125000
1$
#130000
0$
#135000
1$
#140000
0$
1(
b10 :
#145000
b100 4
1$
#150000
0$
#155000
b101 4
1$
#160000
0$
0(
#165000
1$
#170000
0$
#175000
1$
#180000
0$
1(
b11 :
#185000
b110 4
1$
#190000
0$
#195000
b111 4
1$
#200000
0$
0(
#205000
1$
#210000
0$
#215000
1$
#220000
0$
1(
b100 :
#225000
b1000 4
1$
#230000
0$
#235000
b1001 4
1$
#240000
0$
0(
#245000
1$
#250000
0$
#255000
1$
#260000
0$
1(
b101 :
#265000
b1010 4
1$
#270000
0$
#275000
b1011 4
1$
#280000
0$
0(
#285000
1$
#290000
0$
#295000
1$
#300000
0$
1(
b110 :
#305000
b1100 4
1$
#310000
0$
#315000
b1101 4
1$
#320000
0$
0(
#325000
1$
#330000
0$
#335000
1$
#340000
0$
1(
b111 :
#345000
b1110 4
1$
#350000
0$
#355000
b1111 4
1$
#360000
0$
0(
#365000
1$
#370000
0$
#375000
1$
#380000
0$
1(
b1000 :
#385000
b10000 4
1$
#390000
0$
#395000
b10001 4
1$
#400000
0$
0(
#405000
1$
#410000
0$
#415000
1$
#420000
0$
1(
b1001 :
#425000
b10010 4
1$
#430000
0$
#435000
b10011 4
1$
#440000
0$
0(
#445000
1$
#450000
0$
#455000
1$
#460000
0$
1(
b1010 :
#465000
b10100 4
1$
#470000
0$
#475000
b10101 4
1$
#480000
0$
0(
#485000
1$
#490000
0$
#495000
1$
#500000
0$
1(
b1011 :
#505000
b10110 4
1$
#510000
0$
#515000
b10111 4
1$
#520000
0$
0(
#525000
1$
#530000
0$
#535000
1$
#540000
0$
1(
b1100 :
#545000
b11000 4
1$
#550000
0$
#555000
b11001 4
1$
#560000
0$
0(
#565000
1$
#570000
0$
#575000
1$
#580000
0$
1(
b1101 :
#585000
b11010 4
1$
#590000
0$
#595000
b11011 4
1$
#600000
0$
0(
#605000
1$
#610000
0$
#615000
1$
#620000
0$
1(
b1110 :
#625000
b11100 4
1$
#630000
0$
#635000
b11101 4
1$
#640000
0$
0(
#645000
1$
#650000
0$
#655000
1$
#660000
0$
1(
b1111 :
#665000
b11110 4
1$
#670000
0$
#675000
b11111 4
1$
#680000
0$
0(
#685000
1$
#690000
0$
#695000
1$
#700000
0$
1(
1%
b10000 :
#705000
07
10
1$
#710000
0$
#715000
1$
#720000
0$
0(
#725000
1$
#730000
0$
#735000
1$
#740000
0$
1(
#745000
1$
#750000
0$
#755000
1$
#760000
0$
0(
#765000
1$
#770000
0$
#775000
1$
#780000
0$
1(
#785000
1$
#790000
0$
#795000
1$
#800000
0$
0(
#805000
1$
#810000
0$
#815000
1$
#820000
0$
1(
#825000
1$
#830000
0$
#835000
1$
#840000
0$
0(
#845000
1$
#850000
0$
#855000
1$
#860000
0$
1(
#865000
1$
#870000
0$
#875000
1$
#880000
0$
0(
#885000
1$
#890000
0$
#895000
1$
#900000
0$
1(
#905000
1$
#910000
0$
#915000
1$
#920000
0$
0(
#925000
1$
#930000
0$
#935000
1$
#940000
0$
1(
1&
b0 :
0%
b1 9
#945000
b0 4
17
00
1$
#950000
0$
#955000
b1 4
b1000000000000000 5
1$
#960000
0$
0(
#965000
1$
#970000
0$
#975000
1$
#980000
0$
1(
0&
b1 :
#985000
b10 4
b100000000000000 5
1$
#990000
0$
#995000
b11 4
b10000000000000 5
1$
#1000000
0$
0(
#1005000
1$
#1010000
0$
#1015000
1$
#1020000
0$
1(
b10 :
#1025000
b100 4
b1000000000000 5
1$
#1030000
0$
#1035000
b101 4
b100000000000 5
1$
#1040000
0$
0(
#1045000
1$
#1050000
0$
#1055000
1$
#1060000
0$
1(
b11 :
#1065000
b110 4
b10000000000 5
1$
#1070000
0$
#1075000
b111 4
b1000000000 5
1$
#1080000
0$
0(
#1085000
1$
#1090000
0$
#1095000
1$
#1100000
0$
1(
b100 :
#1105000
b1000 4
b100000000 5
1$
#1110000
0$
#1115000
b1001 4
b10000000 5
1$
#1120000
0$
0(
#1125000
1$
#1130000
0$
#1135000
1$
#1140000
0$
1(
b101 :
#1145000
b1010 4
b1000000 5
1$
#1150000
0$
#1155000
b1011 4
b100000 5
1$
#1160000
0$
0(
#1165000
1$
#1170000
0$
#1175000
1$
#1180000
0$
1(
b110 :
#1185000
b1100 4
b10000 5
1$
#1190000
0$
#1195000
b1101 4
b1000 5
1$
#1200000
0$
0(
#1205000
1$
#1210000
0$
#1215000
1$
#1220000
0$
1(
b111 :
#1225000
b1110 4
b100 5
1$
#1230000
0$
#1235000
b1111 4
b10 5
1$
#1240000
0$
0(
#1245000
1$
#1250000
0$
#1255000
1$
#1260000
0$
1(
b1000 :
#1265000
b10000 4
b1 5
1$
#1270000
0$
#1275000
b10001 4
b0 5
1$
#1280000
0$
0(
#1285000
1$
#1290000
0$
#1295000
1$
#1300000
0$
1(
b1001 :
#1305000
b10010 4
1$
#1310000
0$
#1315000
b10011 4
1$
#1320000
0$
0(
#1325000
1$
#1330000
0$
#1335000
1$
#1340000
0$
1(
b1010 :
#1345000
b10100 4
1$
#1350000
0$
#1355000
b10101 4
1$
#1360000
0$
0(
#1365000
1$
#1370000
0$
#1375000
1$
#1380000
0$
1(
b1011 :
#1385000
b10110 4
1$
#1390000
0$
#1395000
b10111 4
1$
#1400000
0$
0(
#1405000
1$
#1410000
0$
#1415000
1$
#1420000
0$
1(
b1100 :
#1425000
b11000 4
1$
#1430000
0$
#1435000
b11001 4
1$
#1440000
0$
0(
#1445000
1$
#1450000
0$
#1455000
1$
#1460000
0$
1(
b1101 :
#1465000
b11010 4
1$
#1470000
0$
#1475000
b11011 4
1$
#1480000
0$
0(
#1485000
1$
#1490000
0$
#1495000
1$
#1500000
0$
1(
b1110 :
#1505000
b11100 4
1$
#1510000
0$
#1515000
b11101 4
1$
#1520000
0$
0(
#1525000
1$
#1530000
0$
#1535000
1$
#1540000
0$
1(
b1111 :
#1545000
b11110 4
1$
#1550000
0$
#1555000
b11111 4
1$
#1560000
0$
0(
#1565000
1$
#1570000
0$
#1575000
1$
#1580000
0$
1(
1%
b10000 :
#1585000
07
10
1$
#1590000
0$
#1595000
1$
#1600000
0$
0(
#1605000
1$
#1610000
0$
#1615000
1$
#1620000
0$
1(
b0 :
0%
b11111111000000 9
#1625000
b0 4
17
00
1$
#1630000
0$
#1635000
b1 4
1$
#1640000
0$
0(
#1645000
1$
#1650000
0$
#1655000
1$
#1660000
0$
1(
b1 :
#1665000
b10 4
1$
#1670000
0$
#1675000
b11 4
1$
#1680000
0$
0(
#1685000
1$
#1690000
0$
#1695000
1$
#1700000
0$
1(
b10 :
#1705000
b100 4
1$
#1710000
0$
#1715000
b101 4
1$
#1720000
0$
0(
#1725000
1$
#1730000
0$
#1735000
1$
#1740000
0$
1(
b11 :
#1745000
b110 4
1$
#1750000
0$
#1755000
b111 4
1$
#1760000
0$
0(
#1765000
1$
#1770000
0$
#1775000
1$
#1780000
0$
1(
b100 :
#1785000
b1000 4
1$
#1790000
0$
#1795000
b1001 4
1$
#1800000
0$
0(
#1805000
1$
#1810000
0$
#1815000
1$
#1820000
0$
1(
b101 :
#1825000
b1010 4
1$
#1830000
0$
#1835000
b1011 4
1$
#1840000
0$
0(
#1845000
1$
#1850000
0$
#1855000
1$
#1860000
0$
1(
1&
b110 :
#1865000
b1100 4
b1000000000000000 5
1$
#1870000
0$
#1875000
b1101 4
b1100000000000000 5
1$
#1880000
0$
0(
#1885000
1$
#1890000
0$
#1895000
1$
#1900000
0$
1(
b111 :
#1905000
b1110 4
b1110000000000000 5
1$
#1910000
0$
#1915000
b1111 4
b1111000000000000 5
1$
#1920000
0$
0(
#1925000
1$
#1930000
0$
#1935000
1$
#1940000
0$
1(
b1000 :
#1945000
b10000 4
b1111100000000000 5
1$
#1950000
0$
#1955000
b10001 4
b1111110000000000 5
1$
#1960000
0$
0(
#1965000
1$
#1970000
0$
#1975000
1$
#1980000
0$
1(
b1001 :
#1985000
b10010 4
b1111111000000000 5
1$
#1990000
0$
#1995000
b10011 4
b1111111100000000 5
1$
#2000000
0$
0(
#2005000
1$
#2010000
0$
#2015000
1$
#2020000
0$
1(
b1010 :
#2025000
b10100 4
b1111111110000000 5
1$
#2030000
0$
#2035000
b10101 4
b1111111111000000 5
1$
#2040000
0$
0(
#2045000
1$
#2050000
0$
#2055000
1$
#2060000
0$
1(
b1011 :
#2065000
b10110 4
b1111111111100000 5
1$
#2070000
0$
#2075000
b10111 4
b1111111111110000 5
1$
#2080000
0$
0(
#2085000
1$
#2090000
0$
#2095000
1$
#2100000
0$
1(
b1100 :
#2105000
b11000 4
b1111111111111000 5
1$
#2110000
0$
#2115000
b11001 4
b1111111111111100 5
1$
#2120000
0$
0(
#2125000
1$
#2130000
0$
#2135000
1$
#2140000
0$
1(
b1101 :
#2145000
b11010 4
b1111111111111110 5
1$
#2150000
0$
#2155000
b11011 4
b1111111111111111 5
1$
#2160000
0$
0(
#2165000
1$
#2170000
0$
#2175000
1$
#2180000
0$
1(
0&
b1110 :
#2185000
b11100 4
b111111111111111 5
1$
#2190000
0$
#2195000
b11101 4
b11111111111111 5
1$
#2200000
0$
0(
#2205000
1$
#2210000
0$
#2215000
1$
#2220000
0$
1(
b1111 :
#2225000
b11110 4
b1111111111111 5
1$
#2230000
0$
#2235000
b11111 4
b111111111111 5
1$
#2240000
0$
0(
#2245000
1$
#2250000
0$
#2255000
1$
#2260000
0$
1(
1%
b10000 :
#2265000
07
10
1$
#2270000
0$
#2275000
1$
#2280000
0$
0(
#2285000
1$
#2290000
0$
#2295000
1$
#2300000
0$
1(
#2305000
1$
#2310000
0$
#2315000
1$
#2320000
0$
0(
#2325000
1$
#2330000
0$
#2335000
1$
#2340000
0$
1(
#2345000
1$
#2350000
0$
#2355000
1$
#2360000
0$
0(
#2365000
1$
#2370000
0$
#2375000
1$
#2380000
0$
1(
#2385000
1$
#2390000
0$
#2395000
1$
#2400000
0$
0(
#2405000
1$
#2410000
0$
#2415000
1$
#2420000
0$
1(
#2425000
1$
#2430000
0$
#2435000
1$
#2440000
0$
0(
#2445000
1$
#2450000
0$
#2455000
1$
#2460000
0$
1(
#2465000
1$
#2470000
0$
#2475000
1$
#2480000
0$
0(
#2485000
1$
#2490000
0$
#2495000
1$
#2500000
0$
1(
b0 :
0%
b10 9
#2505000
b0 5
b0 4
17
00
1$
#2510000
0$
#2515000
b1 4
1$
#2520000
0$
0(
#2525000
1$
#2530000
0$
#2535000
1$
#2540000
0$
1(
1&
b1 :
#2545000
b10 4
b1000000000000000 5
1$
#2550000
0$
#2555000
b11 4
b1100000000000000 5
1$
#2560000
0$
0(
#2565000
1$
#2570000
0$
#2575000
1$
#2580000
0$
1(
0&
b10 :
#2585000
b100 4
b110000000000000 5
1$
#2590000
0$
#2595000
b101 4
b11000000000000 5
1$
#2600000
0$
0(
#2605000
1$
#2610000
0$
#2615000
1$
#2620000
0$
1(
b11 :
#2625000
b110 4
b1100000000000 5
1$
#2630000
0$
#2635000
b111 4
b110000000000 5
1$
#2640000
0$
0(
#2645000
1$
#2650000
0$
#2655000
1$
#2660000
0$
1(
b100 :
#2665000
b1000 4
b11000000000 5
1$
#2670000
0$
#2675000
b1001 4
b1100000000 5
1$
#2680000
0$
0(
#2685000
1$
#2690000
0$
#2695000
1$
#2700000
0$
1(
b101 :
#2705000
b1010 4
b110000000 5
1$
#2710000
0$
#2715000
b1011 4
b11000000 5
1$
#2720000
0$
0(
#2725000
1$
#2730000
0$
#2735000
1$
#2740000
0$
1(
b110 :
#2745000
b1100 4
b1100000 5
1$
#2750000
0$
#2755000
b1101 4
b110000 5
1$
#2760000
0$
0(
#2765000
1$
#2770000
0$
#2775000
1$
#2780000
0$
1(
b111 :
#2785000
b1110 4
b11000 5
1$
#2790000
0$
#2795000
b1111 4
b1100 5
1$
#2800000
0$
0(
#2805000
1$
#2810000
0$
#2815000
1$
#2820000
0$
1(
b1000 :
#2825000
b10000 4
b110 5
1$
#2830000
0$
#2835000
b10001 4
b11 5
1$
#2840000
0$
0(
#2845000
1$
#2850000
0$
#2855000
1$
#2860000
0$
1(
b1001 :
#2865000
b10010 4
b1 5
1$
#2870000
0$
#2875000
b10011 4
b0 5
1$
#2880000
0$
0(
#2885000
1$
#2890000
0$
#2895000
1$
#2900000
0$
1(
b1010 :
#2905000
b10100 4
1$
#2910000
0$
#2915000
b10101 4
1$
#2920000
0$
0(
#2925000
1$
#2930000
0$
#2935000
1$
#2940000
0$
1(
b1011 :
#2945000
b10110 4
1$
#2950000
0$
#2955000
b10111 4
1$
#2960000
0$
0(
#2965000
1$
#2970000
0$
#2975000
1$
#2980000
0$
1(
b1100 :
#2985000
b11000 4
1$
#2990000
0$
#2995000
b11001 4
1$
#3000000
0$
0(
#3005000
1$
#3010000
0$
#3015000
1$
#3020000
0$
1(
b1101 :
#3025000
b11010 4
1$
#3030000
0$
#3035000
b11011 4
1$
#3040000
0$
0(
#3045000
1$
#3050000
0$
#3055000
1$
#3060000
0$
1(
b1110 :
#3065000
b11100 4
1$
#3070000
0$
#3075000
b11101 4
1$
#3080000
0$
0(
#3085000
1$
#3090000
0$
#3095000
1$
#3100000
0$
1(
b1111 :
#3105000
b11110 4
1$
#3110000
0$
#3115000
b11111 4
1$
#3120000
0$
0(
#3125000
1$
#3130000
0$
#3135000
1$
#3140000
0$
1(
1%
b10000 :
#3145000
07
10
1$
#3150000
0$
#3155000
1$
#3160000
0$
0(
#3165000
1$
#3170000
0$
#3175000
1$
#3180000
0$
1(
#3185000
1$
#3190000
0$
#3195000
1$
#3200000
0$
0(
#3205000
1$
#3210000
0$
#3215000
1$
#3220000
0$
1(
#3225000
1$
#3230000
0$
#3235000
1$
#3240000
0$
0(
#3245000
1$
#3250000
0$
#3255000
1$
#3260000
0$
1(
#3265000
1$
#3270000
0$
#3275000
1$
#3280000
0$
0(
#3285000
1$
#3290000
0$
#3295000
1$
#3300000
0$
1(
#3305000
1$
#3310000
0$
#3315000
1$
#3320000
0$
0(
#3325000
1$
#3330000
0$
#3335000
1$
#3340000
0$
1(
#3345000
1$
#3350000
0$
#3355000
1$
#3360000
0$
0(
#3365000
1$
#3370000
0$
#3375000
1$
#3380000
0$
1(
1&
b0 :
0%
b11 9
#3385000
b0 4
17
00
1$
#3390000
0$
#3395000
b1 4
b1000000000000000 5
1$
#3400000
0$
0(
#3405000
1$
#3410000
0$
#3415000
1$
#3420000
0$
1(
b1 :
#3425000
b10 4
b1100000000000000 5
1$
#3430000
0$
#3435000
b11 4
b1110000000000000 5
1$
#3440000
0$
0(
#3445000
1$
#3450000
0$
#3455000
1$
#3460000
0$
1(
0&
b10 :
#3465000
b100 4
b111000000000000 5
1$
#3470000
0$
#3475000
b101 4
b11100000000000 5
1$
#3480000
0$
0(
#3485000
1$
#3490000
0$
#3495000
1$
#3500000
0$
1(
b11 :
#3505000
b110 4
b1110000000000 5
1$
#3510000
0$
#3515000
b111 4
b111000000000 5
1$
#3520000
0$
0(
#3525000
1$
#3530000
0$
#3535000
1$
#3540000
0$
1(
b100 :
#3545000
b1000 4
b11100000000 5
1$
#3550000
0$
#3555000
b1001 4
b1110000000 5
1$
#3560000
0$
0(
#3565000
1$
#3570000
0$
#3575000
1$
#3580000
0$
1(
b101 :
#3585000
b1010 4
b111000000 5
1$
#3590000
0$
#3595000
b1011 4
b11100000 5
1$
#3600000
0$
0(
#3605000
1$
#3610000
0$
#3615000
1$
#3620000
0$
1(
b110 :
#3625000
b1100 4
b1110000 5
1$
#3630000
0$
#3635000
b1101 4
b111000 5
1$
#3640000
0$
0(
#3645000
1$
#3650000
0$
#3655000
1$
#3660000
0$
1(
b111 :
#3665000
b1110 4
b11100 5
1$
#3670000
0$
#3675000
b1111 4
b1110 5
1$
#3680000
0$
0(
#3685000
1$
#3690000
0$
#3695000
1$
#3700000
0$
1(
b1000 :
#3705000
b10000 4
b111 5
1$
#3710000
0$
#3715000
b10001 4
b11 5
1$
#3720000
0$
0(
#3725000
1$
#3730000
0$
#3735000
1$
#3740000
0$
1(
b1001 :
#3745000
b10010 4
b1 5
1$
#3750000
0$
#3755000
b10011 4
b0 5
1$
#3760000
0$
0(
#3765000
1$
#3770000
0$
#3775000
1$
#3780000
0$
1(
b1010 :
#3785000
b10100 4
1$
#3790000
0$
#3795000
b10101 4
1$
#3800000
0$
0(
#3805000
1$
#3810000
0$
#3815000
1$
#3820000
0$
1(
b1011 :
#3825000
b10110 4
1$
#3830000
0$
#3835000
b10111 4
1$
#3840000
0$
0(
#3845000
1$
#3850000
0$
#3855000
1$
#3860000
0$
1(
b1100 :
#3865000
b11000 4
1$
#3870000
0$
#3875000
b11001 4
1$
#3880000
0$
0(
#3885000
1$
#3890000
0$
#3895000
1$
#3900000
0$
1(
b1101 :
#3905000
b11010 4
1$
#3910000
0$
#3915000
b11011 4
1$
#3920000
0$
0(
#3925000
1$
#3930000
0$
#3935000
1$
#3940000
0$
1(
b1110 :
#3945000
b11100 4
1$
#3950000
0$
#3955000
b11101 4
1$
#3960000
0$
0(
#3965000
1$
#3970000
0$
#3975000
1$
#3980000
0$
1(
b1111 :
#3985000
b11110 4
1$
#3990000
0$
#3995000
b11111 4
1$
#4000000
0$
0(
